Workbook

Sheet familia
A1: id_familia | B1: nombre_familia
A2: 1 | B2: Mercados financieros | C2: =+A2 -> 1
A3: 2 | B3: Precios Internacionales | C3: =+A3 -> 2
A4: 3 | B4: Precios y salarios | C4: =+A4 -> 3

Sheet sub_familia
A1: id_sub_familia | B1: nombre_sub_familia | D1: id_familia
A2: 1 | B2: Materias primas | C2: =+A2 -> 1 | D2: 2
A3: 2 | B3: Precio de exportación | C3: =+A3 -> 2 | D3: 3
A4: 3 | B4: Precio interno de cadena transable | C4: =+A4 -> 3 | D4: 3
A5: 4 | B5: Precios | C5: =+A5 -> 4 | D5: 3
A6: 5 | B6: Salarios | C6: =+A6 -> 5 | D6: 3
A7: 6 | B7: Servicios | C7: =+A7 -> 6 | D7: 2
A8: 7 | B8: Tipo de cambio | C8: =+A8 -> 7 | D8: 1

Sheet Sheet1_old
A1: id | B1: nombre | C1: id_nombre_variable | D1: id_region | E1: pais/region | F1: familia | G1: sub_familia | H1: id_familia | I1: id_sub_familia | J1: categoria | K1: fuente | L1: periodicidad | M1: unidad | N1: activo | O1: moneda | P1: nominal_real | Q1: link | R1: mercado | S1: es_cotizacion
A2: 1 | B2: Precio hacienda - INAC | C2: 12 | D2: 12 | E2: Uruguay | F2: Precios y salarios | G2: Precio interno de cadena transable | H2: 3 | I2: 3 | J2: P | K2: INAC – serie mensual precios de hacienda | L2: M | M2: USD/kg | N2: 1 | O2: usd | P2: n | S2: 0
A3: 2 | B3: Leche en polvo - INALE | C3: 10 | D3: 12 | E3: Uruguay | F3: Precios y salarios | G3: Precio de exportación | H3: 3 | I3: 2 | J3: P | K3: INALE – Exportación leche en polvo entera | L3: M | M3: USD/ton | N3: 1 | O3: usd | P3: n | S3: 0
A4: 3 | B4: Queso - INALE | C4: 14 | D4: 12 | E4: Uruguay | F4: Precios y salarios | G4: Precio de exportación | H4: 3 | I4: 2 | J4: P | K4: INALE – Exportación queso | L4: M | M4: USD/ton | N4: 1 | O4: usd | P4: n | S4: 0
A5: 4 | B5: Precio leche productor - INALE | C5: 13 | D5: 12 | E5: Uruguay | F5: Precios y salarios | G5: Precio interno de cadena transable | H5: 3 | I5: 3 | J5: P | K5: INALE – Precio leche en tambo y composición | L5: M | M5: UYU/litro | N5: 1 | O5: usd | P5: n | S5: 0
A6: 5 | B6: Precio carne export - INAC | C6: 11 | D6: 12 | E6: Uruguay | F6: Precios y salarios | G6: Precio de exportación | H6: 3 | I6: 2 | J6: P | K6: INALE – Precio leche en tambo y composición | L6: W | M6: USD/ton | N6: 1 | O6: usd | P6: n | S6: 0
A7: 6 | B7: USD/LC | C7: 20 | D7: 12 | E7: Uruguay | F7: Financiero | G7: Tipo de cambio | H7: 1 | I7: 7 | K7: INE | L7: D | M7: UYU por USD | N7: 1 | P7: n | S7: 1
A8: 7 | B8: EUR/LC | C8: 6 | D8: 12 | E8: Uruguay | F8: Financiero | G8: Tipo de cambio | H8: 1 | I8: 7 | K8: INE | L8: D | M8: UYU por EUR | N8: 1 | P8: n | S8: 0
A9: 8 | B9: Soja | C9: 18 | D9: 11 | E9: Economía internacional | F9: Precio Internacional | G9: Materias primas | H9: 2 | I9: 1 | J9: P | K9: WorldBank_CMO | L9: M | M9: USD/ton | N9: 1 | O9: usd | P9: n | S9: 0
A10: 9 | B10: Arroz | C10: 2 | D10: 11 | E10: Economía internacional | F10: Precio Internacional | G10: Materias primas | H10: 2 | I10: 1 | J10: P | K10: WorldBank_CMO | L10: M | M10: USD/ton | N10: 1 | O10: usd | P10: n | S10: 0
A11: 10 | B11: Trigo | C11: 19 | D11: 11 | E11: Economía internacional | F11: Precio Internacional | G11: Materias primas | H11: 2 | I11: 1 | J11: P | K11: WorldBank_CMO | L11: M | M11: USD/ton | N11: 1 | O11: usd | P11: n | S11: 0
A12: 11 | B12: IPC | C12: 9 | D12: 12 | E12: Uruguay | F12: Precios y salarios | G12: Precios | H12: 3 | I12: 4 | K12: INE | L12: M | M12: Indice | N12: 1 | P12: n | S12: 0
A13: 12 | B13: Celulosa -indice- | C13: 4 | D13: 11 | E13: Economía internacional | F13: Precio Internacional | G13: Materias primas | H13: 2 | I13: 1 | J13: P | K13: INSEE - serie 010600341 (Producer Price Index - Pulp) | L13: M | M13: Indice | N13: 1 | O13: eur | P13: n | S13: 0
A14: 13 | B14: Software | C14: 17 | D14: 11 | E14: Economía internacional | F14: Precio Internacional | G14: Servicios | H14: 2 | I14: 6 | J14: S | K14: BLS | L14: M | M14: Indice | N14: 1 | O14: usd | P14: n | Q14: https://data.bls.gov/dataViewer/view/timeseries/PCU513210513210 | S14: 0
A15: 14 | B15: Ingeniería | C15: 8 | D15: 11 | E15: Economía internacional | F15: Precio Internacional | G15: Servicios | H15: 2 | I15: 6 | J15: S | K15: BLS | L15: M | M15: Indice | N15: 1 | O15: usd | P15: n | Q15: https://data.bls.gov/dataViewer/view/timeseries/PCU541330541330 | S15: 0
A16: 15 | B16: Arquitectura | C16: 1 | D16: 11 | E16: Economía internacional | F16: Precio Internacional | G16: Servicios | H16: 2 | I16: 6 | J16: S | K16: BLS | L16: M | M16: Indice | N16: 1 | O16: usd | P16: n | Q16: https://data.bls.gov/dataViewer/view/timeseries/PCU541310541310 | S16: 0
A17: 16 | B17: Contabilidad (CPA) | C17: 5 | D17: 11 | E17: Economía internacional | F17: Precio Internacional | G17: Servicios | H17: 2 | I17: 6 | J17: S | K17: BLS | L17: M | M17: Indice | N17: 1 | O17: usd | P17: n | Q17: https://data.bls.gov/dataViewer/view/timeseries/PCU541211541211 | S17: 0
A18: 17 | B18: Bookkeeping / payroll | C18: 3 | D18: 11 | E18: Economía internacional | F18: Precio Internacional | G18: Servicios | H18: 2 | I18: 6 | J18: S | K18: BLS | L18: M | M18: Indice | N18: 1 | O18: usd | P18: n | Q18: https://data.bls.gov/dataViewer/view/timeseries/PCU541211541211A | S18: 0
A19: 18 | B19: Servicios no tradicionales - sin software | C19: 16 | D19: 11 | E19: Economía internacional | F19: Precio Internacional | G19: Servicios | H19: 2 | I19: 6 | J19: S | K19: BLS | L19: M | M19: Indice | N19: 1 | O19: usd | P19: n | S19: 0
A20: 19 | B20: Salario real | C20: 15 | D20: 12 | E20: Uruguay | F20: Precios y salarios | G20: Salarios | H20: 3 | I20: 5 | J20: I | K20: INE | L20: M | M20: Indice | N20: 1 | O20: uyu | P20: r | S20: 0
A21: 20 | B21: Gasoil | C21: 7 | D21: 12 | E21: Uruguay | F21: Precios y salarios | G21: Precios | H21: 3 | I21: 4 | J21: I | K21: ANCAP | L21: M | M21: $ por Litro | N21: 1 | O21: uyu | P21: n | S21: 0
A22: 22 | B22: USD/LC -informal- | C22: 21 | D22: 1 | E22: Argentina | F22: Financiero | G22: Tipo de cambio | H22: 1 | I22: 7 | K22: Rava_Scraping | L22: D | M22: ARS por USD | N22: 1 | O22: usd | P22: n | S22: 1
A23: 23 | B23: USD/LC | C23: 20 | D23: 3 | E23: Brasil | F23: Financiero | G23: Tipo de cambio | H23: 1 | I23: 7 | K23: BCB_API_PTAX | L23: D | M23: BRL por USD | N23: 1 | O23: usd | P23: n | S23: 1
A24: 24 | B24: USD/LC | C24: 20 | D24: 10 | E24: Perú | F24: Financiero | G24: Tipo de cambio | H24: 1 | I24: 7 | K24: BCRP_API | L24: D | M24: PEN por USD | N24: 1 | O24: usd | P24: n | S24: 1
A25: 25 | B25: USD/LC | C25: 20 | D25: 4 | E25: Chile | F25: Financiero | G25: Tipo de cambio | H25: 1 | I25: 7 | K25: BCCH_API | L25: D | M25: CLP por USD | N25: 1 | O25: usd | P25: n | S25: 1
A26: 26 | B26: USD/LC | C26: 20 | D26: 6 | E26: México | F26: Financiero | G26: Tipo de cambio | H26: 1 | I26: 7 | K26: BCCH_API | L26: D | M26: MXN por USD | N26: 1 | O26: MXN | P26: n | S26: 1
A27: 27 | B27: USD/LC | C27: 20 | D27: 5 | E27: Colombia | F27: Financiero | G27: Tipo de cambio | H27: 1 | I27: 7 | K27: BCCH_API | L27: D | M27: COP por USD | N27: 1 | O27: COP | P27: n | S27: 1
A28: 28 | B28: USD/LC | C28: 20 | D28: 2 | E28: Australia | F28: Financiero | G28: Tipo de cambio | H28: 1 | I28: 7 | K28: BCCH_API | L28: D | M28: AUD por USD | N28: 1 | O28: AUD | P28: n | S28: 1
A29: 29 | B29: USD/LC | C29: 20 | D29: 7 | E29: Nueva Zelanda | F29: Financiero | G29: Tipo de cambio | H29: 1 | I29: 7 | K29: BCCH_API | L29: D | M29: NZD por USD | N29: 1 | O29: NZD | P29: n | S29: 1
A30: 30 | B30: USD/LC | C30: 20 | D30: 13 | E30: Sudáfrica | F30: Financiero | G30: Tipo de cambio | H30: 1 | I30: 7 | K30: BCCH_API | L30: D | M30: ZAR por USD | N30: 1 | O30: ZAR | P30: n | S30: 1
A31: 31 | B31: USD/LC | C31: 20 | D31: 8 | E31: Paraguay | F31: Financiero | G31: Tipo de cambio | H31: 1 | I31: 7 | K31: BCCH_API | L31: D | M31: PYG por USD | N31: 1 | O31: PYG | P31: n | S31: 1
A32: 32 | B32: USD/LC | C32: 20 | D32: 1 | E32: Argentina | F32: Financiero | G32: Tipo de cambio | H32: 1 | I32: 7 | K32: BCCH_API | L32: D | M32: ARS por USD | N32: 1 | O32: ARS | P32: n | S32: 1
A33: 33 | B33: IPC | C33: 9 | D33: 4 | E33: Chile | F33: Precios y salarios | G33: Precios | H33: 3 | I33: 4 | K33: BCCH_API | L33: M | M33: Índice | N33: 1 | P33: n | S33: 0
A34: 34 | B34: IPC | C34: 9 | D34: 3 | E34: Brasil | F34: Precios y salarios | G34: Precios | H34: 3 | I34: 4 | K34: BCB_API | L34: M | M34: Índice | N34: 1 | P34: n | S34: 0
A35: 35 | B35: IPC | C35: 9 | D35: 6 | E35: México | F35: Precios y salarios | G35: Precios | H35: 3 | I35: 4 | K35: BANXICO_API | L35: M | M35: Índice | N35: 1 | P35: n | S35: 0
A36: 36 | B36: IPC | C36: 9 | D36: 9 | E36: Perú | F36: Precios y salarios | G36: Precios | H36: 3 | I36: 4 | K36: BCRP_HTML | L36: M | M36: Índice | N36: 1 | P36: n | S36: 0

Sheet maestro
A1: id_variable | B1: id_pais | C1: fuente | D1: periodicidad | E1: activo | F1: link
A2: 12 | B2: 858 | C2: INAC – serie mensual precios de hacienda | D2: M | E2: 1
A3: 10 | B3: 858 | C3: INALE – Exportación leche en polvo entera | D3: M | E3: 1
A4: 14 | B4: 858 | C4: INALE – Exportación queso | D4: M | E4: 1
A5: 13 | B5: 858 | C5: INALE – Precio leche en tambo y composición | D5: M | E5: 1
A6: 11 | B6: 858 | C6: INALE – Precio leche en tambo y composición | D6: W | E6: 1
A7: 20 | B7: 858 | C7: INE | D7: D | E7: 1
A8: 6 | B8: 858 | C8: INE | D8: D | E8: 1
A9: 18 | B9: 999 | C9: WorldBank_CMO | D9: M | E9: 1
A10: 2 | B10: 999 | C10: WorldBank_CMO | D10: M | E10: 1
A11: 19 | B11: 999 | C11: WorldBank_CMO | D11: M | E11: 1
A12: 9 | B12: 858 | C12: INE | D12: M | E12: 1
A13: 4 | B13: 999 | C13: INSEE - serie 010600341 (Producer Price Index - Pulp) | D13: M | E13: 1
A14: 17 | B14: 999 | C14: BLS | D14: M | E14: 1 | F14: https://data.bls.gov/dataViewer/view/timeseries/PCU513210513210
A15: 8 | B15: =+B14 -> 999 | C15: BLS | D15: M | E15: 1 | F15: https://data.bls.gov/dataViewer/view/timeseries/PCU541330541330
A16: 1 | B16: =+B15 -> 999 | C16: BLS | D16: M | E16: 1 | F16: https://data.bls.gov/dataViewer/view/timeseries/PCU541310541310
A17: 5 | B17: =+B16 -> 999 | C17: BLS | D17: M | E17: 1 | F17: https://data.bls.gov/dataViewer/view/timeseries/PCU541211541211
A18: 3 | B18: =+B17 -> 999 | C18: BLS | D18: M | E18: 1 | F18: https://data.bls.gov/dataViewer/view/timeseries/PCU541211541211A
A19: 16 | B19: =+B18 -> 999 | C19: BLS | D19: M | E19: 1
A20: 15 | B20: 858 | C20: INE | D20: M | E20: 1
A21: 7 | B21: 858 | C21: ANCAP | D21: M | E21: 1
A22: 21 | B22: 32 | C22: Rava_Scraping | D22: D | E22: 1
A23: 20 | B23: 76 | C23: BCB_API_PTAX | D23: D | E23: 1
A24: 20 | B24: 604 | C24: BCRP_API | D24: D | E24: 1
A25: 20 | B25: 152 | C25: BCCH_API | D25: D | E25: 1
A26: 20 | B26: 484 | C26: BCCH_API | D26: D | E26: 1
A27: 20 | B27: 170 | C27: BCCH_API | D27: D | E27: 1
A28: 20 | B28: 36 | C28: BCCH_API | D28: D | E28: 1
A29: 20 | B29: 554 | C29: BCCH_API | D29: D | E29: 1
A30: 20 | B30: 710 | C30: BCCH_API | D30: D | E30: 1
A31: 20 | B31: 600 | C31: BCCH_API | D31: D | E31: 1
... A36: 9 | B36: 604 | C36: BCRP_HTML | D36: M | E36: 1

Sheet pais_grupo
A1: PAÍS | B1: id_pais
A2: Afganistán | B2: 4
A3: Albania | B3: 8
A4: Alemania | B4: 276
A5: Andorra | B5: 20
A6: Angola | B6: 24
A7: Anguila | B7: 660
A8: Antártida | B8: 10
A9: Antigua y Barbuda | B9: 28
A10: Antillas Neerlandesas | B10: 530
A11: Arabia Saudita | B11: 682
A12: Argelia | B12: 12
A13: Argentina | B13: 32
... A242: Economía internacional | B242: 999

Sheet variables
A1: id_variable | B1: id_nombre_variable | C1: id_sub_familia | D1: nominal_o_real | E1: moneda
A2: 1 | B2: Servicios de arquitectura | C2: =+VLOOKUP(A2,Sheet1_old!C:I,7,FALSE) -> 6 | D2: n | E2: usd
A3: 2 | B3: Arroz | C3: =+VLOOKUP(A3,Sheet1_old!C:I,7,FALSE) -> 1 | D3: =+D2 -> n | E3: =+E2 -> usd
A4: 3 | B4: Servicios de Bookkeeping / payroll | C4: =+VLOOKUP(A4,Sheet1_old!C:I,7,FALSE) -> 6 | D4: =+D3 -> n | E4: =+E3 -> usd
A5: 4 | B5: Celulosa -indice- | C5: =+VLOOKUP(A5,Sheet1_old!C:I,7,FALSE) -> 1 | D5: =+D4 -> n | E5: eur
A6: 5 | B6: Servicios de Contabilidad (CPA) | C6: =+VLOOKUP(A6,Sheet1_old!C:I,7,FALSE) -> 6 | D6: =+D5 -> n | E6: usd
A7: 6 | B7: EUR/LC | C7: =+VLOOKUP(A7,Sheet1_old!C:I,7,FALSE) -> 7 | D7: n | E7: eur
A8: 7 | B8: Gasoil | C8: =+VLOOKUP(A8,Sheet1_old!C:I,7,FALSE) -> 4 | D8: =+D7 -> n | E8: lc
A9: 8 | B9: Servicios de consultoría en ingeniería | C9: =+VLOOKUP(A9,Sheet1_old!C:I,7,FALSE) -> 6 | D9: =+D8 -> n | E9: usd
A10: 9 | B10: IPC | C10: =+VLOOKUP(A10,Sheet1_old!C:I,7,FALSE) -> 4 | D10: n | E10: lc
A11: 10 | B11: Leche en polvo - INALE | C11: =+VLOOKUP(A11,Sheet1_old!C:I,7,FALSE) -> 2 | D11: n | E11: usd
A12: 11 | B12: Precio carne export - INAC | C12: =+VLOOKUP(A12,Sheet1_old!C:I,7,FALSE) -> 2 | D12: n | E12: usd
A13: 12 | B13: Precio hacienda - INAC | C13: =+VLOOKUP(A13,Sheet1_old!C:I,7,FALSE) -> 3 | D13: n | E13: usd
A14: 13 | B14: Precio leche productor - INALE | C14: =+VLOOKUP(A14,Sheet1_old!C:I,7,FALSE) -> 3 | D14: n | E14: usd
A15: 14 | B15: Queso - INALE | C15: =+VLOOKUP(A15,Sheet1_old!C:I,7,FALSE) -> 2 | D15: n | E15: usd
A16: 15 | B16: Salario real | C16: =+VLOOKUP(A16,Sheet1_old!C:I,7,FALSE) -> 5 | D16: r | E16: lc
A17: 16 | B17: Servicios no tradicionales - sin software | C17: =+VLOOKUP(A17,Sheet1_old!C:I,7,FALSE) -> 6 | D17: n | E17: usd
A18: 17 | B18: Servicios de software | C18: =+VLOOKUP(A18,Sheet1_old!C:I,7,FALSE) -> 6 | D18: n | E18: usd
A19: 18 | B19: Soja | C19: =+VLOOKUP(A19,Sheet1_old!C:I,7,FALSE) -> 1 | D19: n | E19: usd
A20: 19 | B20: Trigo | C20: =+VLOOKUP(A20,Sheet1_old!C:I,7,FALSE) -> 1 | D20: n | E20: usd
A21: 20 | B21: USD/LC | C21: =+VLOOKUP(A21,Sheet1_old!C:I,7,FALSE) -> 7 | D21: n | E21: lc
A22: 21 | B22: USD/LC -informal- | C22: =+VLOOKUP(A22,Sheet1_old!C:I,7,FALSE) -> 7 | D22: n | E22: lc

Sheet filtros_graph_pais
A1: id_graph | B1: id_pais
A2: 2 | B2: 32
A3: =+A2 -> 2 | B3: 76
A4: =+A3 -> 2 | B4: 604
A5: =+A4 -> 2 | B5: 152
A6: =+A5 -> 2 | B6: 484
A7: =+A6 -> 2 | B7: 170
A8: =+A7 -> 2 | B8: 36
A9: =+A8 -> 2 | B9: 554
A10: =+A9 -> 2 | B10: 710
A11: =+A10 -> 2 | B11: 600
A12: =+A11 -> 2 | B12: 32
A13: =+A12 -> 2 | B13: 858
A14: 3 | B14: 858
A15: =+A14 -> 3 | B15: 152
A16: =+A15 -> 3 | B16: 76
A17: =+A16 -> 3 | B17: 484
A18: 3 | B18: 604

Sheet graph
A1: id_graph | B1: nombre_graph | C1: selector
A2: 1 | B2: Precios de Exportación en Pesos Uruguayos Constantes | C2: Seleccione producto
A3: 2 | B3: Cotizaciones de monedas | C3: Seleccione país
A4: 3 | B4: Inflación en dólares | C4: Seleccione país
A5: 4 | B5: Precios de Exportación -corrientes- | C5: Seleccione producto
